madrassati_exercise_perseus_plugin/__init__.py
madrassati_exercise_perseus_plugin/madrassati_plugin.py
madrassati_exercise_perseus_plugin/build/madrassati_exercise_perseus_plugin.main_stats.json
madrassati_exercise_perseus_plugin/locale/ar/LC_MESSAGES/madrassati_exercise_perseus_plugin.main-messages.json
madrassati_exercise_perseus_plugin/locale/en/LC_MESSAGES/madrassati_exercise_perseus_plugin.main-messages.json
madrassati_exercise_perseus_plugin/locale/fr_FR/LC_MESSAGES/madrassati_exercise_perseus_plugin.main-messages.json
madrassati_exercise_perseus_plugin/static/fonts/Symbola.eot
madrassati_exercise_perseus_plugin/static/fonts/Symbola.ttf
madrassati_exercise_perseus_plugin/static/fonts/Symbola.woff
madrassati_exercise_perseus_plugin/static/images/spinner.gif
madrassati_exercise_perseus_plugin/static/madrassati_exercise_perseus_plugin.main/madrassati_exercise_perseus_plugin.main-1.3.6.1.js
madrassati_exercise_perseus_plugin/static/madrassati_exercise_perseus_plugin.main/madrassati_exercise_perseus_plugin.main-1.3.6.1.js.map
madrassati_exercise_perseus_plugin/static/madrassati_exercise_perseus_plugin.main/madrassati_exercise_perseus_plugin.main-extra-widgets-1.3.6.1.js
madrassati_exercise_perseus_plugin/static/madrassati_exercise_perseus_plugin.main/madrassati_exercise_perseus_plugin.main-extra-widgets-1.3.6.1.js.map
madrassati_exercise_perseus_plugin/static/madrassati_exercise_perseus_plugin.main/madrassati_exercise_perseus_plugin.main1.3.6.1.css
madrassati_exercise_perseus_plugin/static/madrassati_exercise_perseus_plugin.main/madrassati_exercise_perseus_plugin.main1.3.6.1.rtl.css
madrassati_exercise_perseus_plugin/static/mathjax/.git
madrassati_exercise_perseus_plugin/static/mathjax/kathjax-config.js
madrassati_exercise_perseus_plugin/static/mathjax/kathjax.py
madrassati_exercise_perseus_plugin/static/mathjax/2.1/MathJax.js
madrassati_exercise_perseus_plugin/static/mathjax/2.1/config/KAthJax-730d56e87e9c926b91584f6030314815.js
madrassati_exercise_perseus_plugin-1.3.6.1.dist-info/METADATA
madrassati_exercise_perseus_plugin-1.3.6.1.dist-info/RECORD
madrassati_exercise_perseus_plugin-1.3.6.1.dist-info/WHEEL
madrassati_exercise_perseus_plugin-1.3.6.1.dist-info/entry_points.txt
madrassati_exercise_perseus_plugin-1.3.6.1.dist-info/top_level.txt
