Metadata-Version: 2.1
Name: madrassati-exercise-perseus-plugin
Version: 1.3.6.1
Summary: madrassati plugin for rendering Khan Academy Perseus style exercises
Home-page: https://github.com/EDUC-EMM/madrassati-exercise-perseus-plugin
Author: Madrassati
Author-email: info@madrassati.dz
License: MIT
Keywords: madrassati
Platform: UNKNOWN
Classifier: Development Status :: 2 - Pre-Alpha
Classifier: Intended Audience :: Developers
Classifier: License :: OSI Approved :: MIT License
Classifier: Natural Language :: English
Classifier: Programming Language :: Python :: 2
Classifier: Programming Language :: Python :: 2.7
Classifier: Programming Language :: Python :: 3
Classifier: Programming Language :: Python :: 3.3
Classifier: Programming Language :: Python :: 3.4
Classifier: Programming Language :: Python :: 3.5
Classifier: Programming Language :: Python :: Implementation :: PyPy
